{
  "kind": "youtube#videoListResponse",
  "etag": "\"XpPGQXPnxQJhLgs6enD_n8JR4Qk/3AzXh8-EABw9PheEGZvInSzPuvQ\"",
  "nextPageToken": "CAUQAA",
  "pageInfo": {
    "totalResults": 200,
    "resultsPerPage": 5
  },
  "items": [
    {
      "kind": "youtube#video",
      "etag": "\"XpPGQXPnxQJhLgs6enD_n8JR4Qk/hVuBP_GIjLFbRF8_VX9lio0Cb_c\"",
      "id": "qyBPzUe3hNI",
      "snippet": {
        "publishedAt": "2019-05-13T02:21:19.000Z",
        "channelId": "UCQzdMyuz0Lf4zo4uGcEujFw",
        "title": "Game of Thrones | Season 8 Episode 6 | Preview (HBO)",
        "description": "The final season of Game of Thrones airs Sundays at 9PM on HBO.",
        "thumbnails": {
          "default": {
            "url": "https://i.ytimg.com/vi/qyBPzUe3hNI/default.jpg",
            "width": 120,
            "height": 90
          },
          "medium": {
            "url": "https://i.ytimg.com/vi/qyBPzUe3hNI/mqdefault.jpg",
            "width": 320,
            "height": 180
          },
          "high": {
            "url": "https://i.ytimg.com/vi/qyBPzUe3hNI/hqdefault.jpg",
            "width": 480,
            "height": 360
          },
          "standard": {
            "url": "https://i.ytimg.com/vi/qyBPzUe3hNI/sddefault.jpg",
            "width": 640,
            "height": 480
          },
          "maxres": {
            "url": "https://i.ytimg.com/vi/qyBPzUe3hNI/maxresdefault.jpg",
            "width": 1280,
            "height": 720
          }
        },
        "channelTitle": "GameofThrones",
        "tags": [
          "Game of Thrones",
          "Season 8",
          "Clip",
          "Stark",
          "Lannister",
          "HBO",
          "Final Season",
          "GoT"
        ],
        "categoryId": "22",
        "liveBroadcastContent": "none",
        "localized": {
          "title": "Game of Thrones | Season 8 Episode 6 | Preview (HBO)",
          "description": "The final season of Game of Thrones airs Sundays at 9PM on HBO."
        },
        "defaultAudioLanguage": "en"
      }
    },
    {
      "kind": "youtube#video",
      "etag": "\"XpPGQXPnxQJhLgs6enD_n8JR4Qk/ZeCygcDP3Y1TdrKue-kjRBEm1jc\"",
      "id": "QF5_Gg-mlYs",
      "snippet": {
        "publishedAt": "2019-05-12T17:00:51.000Z",
        "channelId": "UCDogdKl7t7NHzQ95aEwkdMw",
        "title": "NIGAHIGA VS SIDEMEN - THE ULTIMATE CHALLENGE",
        "description": "Sidemen Clothing: http://www.sidemenclothing.com\nSub to Nigahiga: https://www.youtube.com/user/nigahiga\n-----------------------------------------------------------------------------------------------------------------------\n\nSidemen:\n● Miniminter: http://www.youtube.com/Miniminter\n● Zerkaa: http://www.youtube.com/Zerkaa\n● Behzinga: http://www.youtube.com/Behzinga\n● Vikkstar123: http://www.youtube.com/Vikkstar123\n● TBJZL: http://www.youtube.com/TBJZL\n● Wroetoshaw: http://www.youtube.com/Wroetoshaw\n● KSI: http://www.youtube.com/KSI",
        "thumbnails": {
          "default": {
            "url": "https://i.ytimg.com/vi/QF5_Gg-mlYs/default.jpg",
            "width": 120,
            "height": 90
          },
          "medium": {
            "url": "https://i.ytimg.com/vi/QF5_Gg-mlYs/mqdefault.jpg",
            "width": 320,
            "height": 180
          },
          "high": {
            "url": "https://i.ytimg.com/vi/QF5_Gg-mlYs/hqdefault.jpg",
            "width": 480,
            "height": 360
          },
          "standard": {
            "url": "https://i.ytimg.com/vi/QF5_Gg-mlYs/sddefault.jpg",
            "width": 640,
            "height": 480
          },
          "maxres": {
            "url": "https://i.ytimg.com/vi/QF5_Gg-mlYs/maxresdefault.jpg",
            "width": 1280,
            "height": 720
          }
        },
        "channelTitle": "Sidemen",
        "tags": [
          "sidemen",
          "nigahiga"
        ],
        "categoryId": "24",
        "liveBroadcastContent": "none",
        "localized": {
          "title": "NIGAHIGA VS SIDEMEN - THE ULTIMATE CHALLENGE",
          "description": "Sidemen Clothing: http://www.sidemenclothing.com\nSub to Nigahiga: https://www.youtube.com/user/nigahiga\n-----------------------------------------------------------------------------------------------------------------------\n\nSidemen:\n● Miniminter: http://www.youtube.com/Miniminter\n● Zerkaa: http://www.youtube.com/Zerkaa\n● Behzinga: http://www.youtube.com/Behzinga\n● Vikkstar123: http://www.youtube.com/Vikkstar123\n● TBJZL: http://www.youtube.com/TBJZL\n● Wroetoshaw: http://www.youtube.com/Wroetoshaw\n● KSI: http://www.youtube.com/KSI"
        }
      }
    },
    {
      "kind": "youtube#video",
      "etag": "\"XpPGQXPnxQJhLgs6enD_n8JR4Qk/dUikkdVIUa9cc8H4cg-6j5kbm9k\"",
      "id": "5MwW1NAsnR8",
      "snippet": {
        "publishedAt": "2019-05-14T00:08:13.000Z",
        "channelId": "UCuaFvcY4MhZY3U43mMt1dYQ",
        "title": "Official Teaser: Disney's Maleficent: Mistress of Evil - In Theaters October 18!",
        "description": "“Maleficent: Mistress of Evil” is a fantasy adventure that picks up several years after “Maleficent,” in which audiences learned of the events that hardened the heart of Disney’s most notorious villain and drove her to curse a baby Princess Aurora. The film continues to explore the complex relationship between the horned fairy and the soon to be Queen as they form new alliances and face new adversaries in their struggle to protect the moors and the magical creatures that reside within. The film is directed by Joachim Rønning from a story by Linda Woolverton and a screenplay by Linda Woolverton and Micah Fitzerman-Blue & Noah Harpster, the film is produced by Joe Roth, Angelina Jolie and Duncan Henderson with Matt Smith, Jeff Kirschenbaum and Michael Vieira serving as executive producers.\n\n \nFacebook: Facebook.com/Maleficent\nTwitter: @Maleficent\nInstagram: @DisneyMaleficent\n#Maleficent",
        "thumbnails": {
          "default": {
            "url": "https://i.ytimg.com/vi/5MwW1NAsnR8/default.jpg",
            "width": 120,
            "height": 90
          },
          "medium": {
            "url": "https://i.ytimg.com/vi/5MwW1NAsnR8/mqdefault.jpg",
            "width": 320,
            "height": 180
          },
          "high": {
            "url": "https://i.ytimg.com/vi/5MwW1NAsnR8/hqdefault.jpg",
            "width": 480,
            "height": 360
          },
          "standard": {
            "url": "https://i.ytimg.com/vi/5MwW1NAsnR8/sddefault.jpg",
            "width": 640,
            "height": 480
          }
        },
        "channelTitle": "Walt Disney Studios",
        "tags": [
          "Disney",
          "Maleficent",
          "Mistress of Evil",
          "Angelina Jolie",
          "Elle Fanning",
          "Joe Roth",
          "Duncan Henderson"
        ],
        "categoryId": "1",
        "liveBroadcastContent": "none",
        "localized": {
          "title": "Official Teaser: Disney's Maleficent: Mistress of Evil - In Theaters October 18!",
          "description": "“Maleficent: Mistress of Evil” is a fantasy adventure that picks up several years after “Maleficent,” in which audiences learned of the events that hardened the heart of Disney’s most notorious villain and drove her to curse a baby Princess Aurora. The film continues to explore the complex relationship between the horned fairy and the soon to be Queen as they form new alliances and face new adversaries in their struggle to protect the moors and the magical creatures that reside within. The film is directed by Joachim Rønning from a story by Linda Woolverton and a screenplay by Linda Woolverton and Micah Fitzerman-Blue & Noah Harpster, the film is produced by Joe Roth, Angelina Jolie and Duncan Henderson with Matt Smith, Jeff Kirschenbaum and Michael Vieira serving as executive producers.\n\n \nFacebook: Facebook.com/Maleficent\nTwitter: @Maleficent\nInstagram: @DisneyMaleficent\n#Maleficent"
        },
        "defaultAudioLanguage": "en"
      }
    },
    {
      "kind": "youtube#video",
      "etag": "\"XpPGQXPnxQJhLgs6enD_n8JR4Qk/DVqL0l_uOugg6JzpKJMGtUvmL80\"",
      "id": "QyB5ofy9RaY",
      "snippet": {
        "publishedAt": "2019-05-11T16:14:01.000Z",
        "channelId": "UC7TTtOQKMXTWWMtWQMIgVSA",
        "title": "FOOD ART CHALLENGE & How To Make the Best Avengers Pokemon Detective Pikachu Pancake Art",
        "description": "We’re back with an all new food twist on the pancake art challenge! This time you'll learn how to make amazing diy food art like Pokémon Detective Pikachu, Iron Man and Spider-Man from Marvel Avengers Endgame, an orbit galaxy from Toy Story 4, Pumba from Lion King and so much more! Try not to laugh as brothers (not twins) the key bros compete in a hilarious do it yourself cooking competition to make homemade delicious art from breakfast and lunch foods like giant IHOP pancakes, watermelon fruit, vegetables and Pizza Hut pizza. And the best part is that you can eat and enjoy it all after! It’s another awesome and funny viral video in this fun entertainment and life hack tutorial compilation series.\n \nJOIN OUR ALL NEW KEYPER CLUB (must be signed into YouTube to join): https://www.youtube.com/channel/UC7TTtOQKMXTWWMtWQMIgVSA/join\n \nGET YOUR MERCH BEFORE ITS SOLD OUT: https://shopcollinskey.com/\n \n#artchallenge #foodart #food #pancakeartchallenge #movie #challenge #howto #diy #avengers #detectivepikachu #fandango\nFOLLOW COLLINS KEY\nInstagram: https://www.instagram.com/collinskey/\nTwitter: https://twitter.com/CollinsKey\nSnapchat: CollinsKey\n \nFOLLOW DEVAN\nInsta: http://bit.ly/1wMSMyu\nTwitter: https://twitter.com/DevanKey\nSnapchat: DevanKey\n \nWatch More Awesome Videos:\nPANCAKE ART CHALLENGE Mystery Wheel & Learn How To Make Fandango Diy Fortnite\nhttps://www.youtube.com/watch?v=ZCg9xHNPR3k\nDogs Pick our Mystery Slime Challenge! Learn How To Make the Best DIY Funny Switch Up\nPANCAKE ART CHALLENGE 3!!! Learn How To Make DIY Pancake!\nhttps://www.youtube.com/watch?v=hpedwgBCqn0\nMaking Food out of Play-Doh! Learn How To Make Diy Edible vs Real Squishy Lunchable Food\n8 Best DIY Food Hacks #2 Plus A New Pancake Art Challenge You Need To Know How To Do\nhttps://www.youtube.com/watch?v=lZgp3WLQjoE\n9 Genius DIY Life Hacks Plus The Best New Art Challenge You Need To Know How To Do\nhttps://www.youtube.com/watch?v=PUvp9fmAAAY",
        "thumbnails": {
          "default": {
            "url": "https://i.ytimg.com/vi/QyB5ofy9RaY/default.jpg",
            "width": 120,
            "height": 90
          },
          "medium": {
            "url": "https://i.ytimg.com/vi/QyB5ofy9RaY/mqdefault.jpg",
            "width": 320,
            "height": 180
          },
          "high": {
            "url": "https://i.ytimg.com/vi/QyB5ofy9RaY/hqdefault.jpg",
            "width": 480,
            "height": 360
          },
          "standard": {
            "url": "https://i.ytimg.com/vi/QyB5ofy9RaY/sddefault.jpg",
            "width": 640,
            "height": 480
          },
          "maxres": {
            "url": "https://i.ytimg.com/vi/QyB5ofy9RaY/maxresdefault.jpg",
            "width": 1280,
            "height": 720
          }
        },
        "channelTitle": "Collins Key",
        "tags": [
          "food art challenge & how to make the best avengers pokemon detective pikachu pancake art",
          "food",
          "art",
          "pancake art challenge",
          "pancake",
          "challenge",
          "pancake art",
          "art challenge",
          "challenges",
          "how to",
          "how",
          "to",
          "make",
          "diy",
          "avengers",
          "avengers endgame",
          "endgame",
          "fandango",
          "best",
          "lion king",
          "pokemon",
          "detective pikachu",
          "lunchable",
          "eat",
          "ihop",
          "collins key",
          "collins",
          "key",
          "tutorial",
          "cooking",
          "pizza hut",
          "real",
          "fun",
          "funny",
          "giant",
          "vs",
          "game",
          "movie",
          "orbit",
          "marvel"
        ],
        "categoryId": "24",
        "liveBroadcastContent": "none",
        "defaultLanguage": "en",
        "localized": {
          "title": "FOOD ART CHALLENGE & How To Make the Best Avengers Pokemon Detective Pikachu Pancake Art",
          "description": "We’re back with an all new food twist on the pancake art challenge! This time you'll learn how to make amazing diy food art like Pokémon Detective Pikachu, Iron Man and Spider-Man from Marvel Avengers Endgame, an orbit galaxy from Toy Story 4, Pumba from Lion King and so much more! Try not to laugh as brothers (not twins) the key bros compete in a hilarious do it yourself cooking competition to make homemade delicious art from breakfast and lunch foods like giant IHOP pancakes, watermelon fruit, vegetables and Pizza Hut pizza. And the best part is that you can eat and enjoy it all after! It’s another awesome and funny viral video in this fun entertainment and life hack tutorial compilation series.\n \nJOIN OUR ALL NEW KEYPER CLUB (must be signed into YouTube to join): https://www.youtube.com/channel/UC7TTtOQKMXTWWMtWQMIgVSA/join\n \nGET YOUR MERCH BEFORE ITS SOLD OUT: https://shopcollinskey.com/\n \n#artchallenge #foodart #food #pancakeartchallenge #movie #challenge #howto #diy #avengers #detectivepikachu #fandango\nFOLLOW COLLINS KEY\nInstagram: https://www.instagram.com/collinskey/\nTwitter: https://twitter.com/CollinsKey\nSnapchat: CollinsKey\n \nFOLLOW DEVAN\nInsta: http://bit.ly/1wMSMyu\nTwitter: https://twitter.com/DevanKey\nSnapchat: DevanKey\n \nWatch More Awesome Videos:\nPANCAKE ART CHALLENGE Mystery Wheel & Learn How To Make Fandango Diy Fortnite\nhttps://www.youtube.com/watch?v=ZCg9xHNPR3k\nDogs Pick our Mystery Slime Challenge! Learn How To Make the Best DIY Funny Switch Up\nPANCAKE ART CHALLENGE 3!!! Learn How To Make DIY Pancake!\nhttps://www.youtube.com/watch?v=hpedwgBCqn0\nMaking Food out of Play-Doh! Learn How To Make Diy Edible vs Real Squishy Lunchable Food\n8 Best DIY Food Hacks #2 Plus A New Pancake Art Challenge You Need To Know How To Do\nhttps://www.youtube.com/watch?v=lZgp3WLQjoE\n9 Genius DIY Life Hacks Plus The Best New Art Challenge You Need To Know How To Do\nhttps://www.youtube.com/watch?v=PUvp9fmAAAY"
        },
        "defaultAudioLanguage": "en"
      }
    },
    {
      "kind": "youtube#video",
      "etag": "\"XpPGQXPnxQJhLgs6enD_n8JR4Qk/oQWehZd3DnZ_rUa5RKNBt1de20I\"",
      "id": "zBkVCpbNnkU",
      "snippet": {
        "publishedAt": "2019-05-12T12:30:04.000Z",
        "channelId": "UCsXVk37bltHxD1rDPwtNM8Q",
        "title": "The Side Effects of Vaccines - How High is the Risk?",
        "description": "Sources: https://sites.google.com/view/sources-vaccines\n\nVaccines are one of our best tools to prevent dangerous diseases, but they come with side effects. So would it be safer not to vaccinate?\n\nThis video has been supported by a grant from the Bill & Melinda Gates Foundation. \n\nIf you are interested how much sponsorships influence our videos, we wrote about that in detail here: https://medium.com/@Kurzgesagt/kurzgesagt-sponsorships-on-youtube-3121a45b0fe9\n\n\nSupport us on Patreon so we can make more videos (and get cool stuff in return): https://www.patreon.com/Kurzgesagt?ty=h\n\nKurzgesagt Newsletter: http://eepurl.com/cRUQxz\nKurzgesagt Merch:  https://bit.ly/2GeuQxZ\nFacebook: http://bit.ly/1NB6U5O\nTwitter: http://bit.ly/2DDeT83\nInstagram: http://bit.ly/2DEN7r3\nDiscord: \nhttps://discordapp.com/invite/GTFf4Tq\n\nThe music of the video here: \nSoundcloud: https://bit.ly/2DZO6kr\nBandcamp: https://bit.ly/2VXep55\nYoutube: https://bit.ly/2CZ6PeN\nFacebook: http://bit.ly/2qW6bY4\n\nTHANKS A LOT TO OUR LOVELY PATRONS FOR SUPPORTING US:Marsha Sohn, Henri Holler, Michelle, Dan Crowley, Alex Hackman, Sammy Mikhael, Marcus Thorén, Kevin Harris, Jayami, Andreas Poletti, David Coates, Omar Galvis, Denny Zavada, Don Knowlton, Sebastian, Jay Ruthnam, Shakira Graham, MatBu, Mikhail, Sinan Taifour, Knowledge Unlimited, Odilia Krause, Anri Digholm, Dominykas, James Gaglio, Alice Jones, Narciso Jaramillo, Qaalid Hashi, Nate Bender, Gulyás Gergely, Michael Bloch, Rick Merced, Etienne Huguenot, Jonathan Lopez, Kai Smith, Benjamin Arndt, Philip Potvin, Amy Halter, Dylan polin, Zach Evans, Karan Chawla, Michael Casey, Francis Bouchard, William Gu, peck neck, Dien Buwono, Patrick Pruitt, Alexander Isayenko, Connor Doherty, Kierr Suñega, Kongpak Phupa, Lewis Foret, Daniel Ingegneri, David Saitta, Soeren Pollerhof, Ravi Shankar, Nico Kooyman, Anna Liceva, Dan Long, ADAM M., Cruz Godar, Pedro Caetano, Jean-Pierre Girard, Jonathan Piedrasanta, Jak SP, Jim Renney, Danielle Mitchell, Giorgio Valli, Ben Evans, Bill Cohen, Gitle Mikkelsen, Gemini00, Benjamin Mahoney, Christopher DiBattista, Mandy Reid, Gary Reckard, Sataporn Chaochonpun, Bigolf, Moses Malone, Kyle Merryman, Dante Bencivenga, Zeus Laser, Jake Wise, Jade, Fontaine Liu, Manav parmar, ethnicolor\n\nHelp us caption & translate this video!https://www.youtube.com/timedtext_cs_panel?c=UCsXVk37bltHxD1rDPwtNM8Q&tab=2",
        "thumbnails": {
          "default": {
            "url": "https://i.ytimg.com/vi/zBkVCpbNnkU/default.jpg",
            "width": 120,
            "height": 90
          },
          "medium": {
            "url": "https://i.ytimg.com/vi/zBkVCpbNnkU/mqdefault.jpg",
            "width": 320,
            "height": 180
          },
          "high": {
            "url": "https://i.ytimg.com/vi/zBkVCpbNnkU/hqdefault.jpg",
            "width": 480,
            "height": 360
          },
          "standard": {
            "url": "https://i.ytimg.com/vi/zBkVCpbNnkU/sddefault.jpg",
            "width": 640,
            "height": 480
          },
          "maxres": {
            "url": "https://i.ytimg.com/vi/zBkVCpbNnkU/maxresdefault.jpg",
            "width": 1280,
            "height": 720
          }
        },
        "channelTitle": "Kurzgesagt – In a Nutshell",
        "tags": [
          "Vaccines",
          "Risk",
          "Side-effects",
          "Child",
          "Vaccinate",
          "Measles",
          "Virus",
          "Flu",
          "MMA",
          "Polio",
          "Pneumonia",
          "Encephalitis",
          "SSPE",
          "Genitalia Imflammation",
          "Memory Cell",
          "Rash",
          "Fever",
          "Immunsystem",
          "Infection",
          "Medicine",
          "Antibodies",
          "Allergic",
          "death",
          "Allergic Reaction",
          "Autism",
          "Healthcare",
          "Health",
          "vaccine",
          "public health",
          "herd immunity",
          "side effects",
          "illness",
          "sickness",
          "human",
          "funny"
        ],
        "categoryId": "27",
        "liveBroadcastContent": "none",
        "defaultLanguage": "en-GB",
        "localized": {
          "title": "The Side Effects of Vaccines - How High is the Risk?",
          "description": "Sources: https://sites.google.com/view/sources-vaccines\n\nVaccines are one of our best tools to prevent dangerous diseases, but they come with side effects. So would it be safer not to vaccinate?\n\nThis video has been supported by a grant from the Bill & Melinda Gates Foundation. \n\nIf you are interested how much sponsorships influence our videos, we wrote about that in detail here: https://medium.com/@Kurzgesagt/kurzgesagt-sponsorships-on-youtube-3121a45b0fe9\n\n\nSupport us on Patreon so we can make more videos (and get cool stuff in return): https://www.patreon.com/Kurzgesagt?ty=h\n\nKurzgesagt Newsletter: http://eepurl.com/cRUQxz\nKurzgesagt Merch:  https://bit.ly/2GeuQxZ\nFacebook: http://bit.ly/1NB6U5O\nTwitter: http://bit.ly/2DDeT83\nInstagram: http://bit.ly/2DEN7r3\nDiscord: \nhttps://discordapp.com/invite/GTFf4Tq\n\nThe music of the video here: \nSoundcloud: https://bit.ly/2DZO6kr\nBandcamp: https://bit.ly/2VXep55\nYoutube: https://bit.ly/2CZ6PeN\nFacebook: http://bit.ly/2qW6bY4\n\nTHANKS A LOT TO OUR LOVELY PATRONS FOR SUPPORTING US:Marsha Sohn, Henri Holler, Michelle, Dan Crowley, Alex Hackman, Sammy Mikhael, Marcus Thorén, Kevin Harris, Jayami, Andreas Poletti, David Coates, Omar Galvis, Denny Zavada, Don Knowlton, Sebastian, Jay Ruthnam, Shakira Graham, MatBu, Mikhail, Sinan Taifour, Knowledge Unlimited, Odilia Krause, Anri Digholm, Dominykas, James Gaglio, Alice Jones, Narciso Jaramillo, Qaalid Hashi, Nate Bender, Gulyás Gergely, Michael Bloch, Rick Merced, Etienne Huguenot, Jonathan Lopez, Kai Smith, Benjamin Arndt, Philip Potvin, Amy Halter, Dylan polin, Zach Evans, Karan Chawla, Michael Casey, Francis Bouchard, William Gu, peck neck, Dien Buwono, Patrick Pruitt, Alexander Isayenko, Connor Doherty, Kierr Suñega, Kongpak Phupa, Lewis Foret, Daniel Ingegneri, David Saitta, Soeren Pollerhof, Ravi Shankar, Nico Kooyman, Anna Liceva, Dan Long, ADAM M., Cruz Godar, Pedro Caetano, Jean-Pierre Girard, Jonathan Piedrasanta, Jak SP, Jim Renney, Danielle Mitchell, Giorgio Valli, Ben Evans, Bill Cohen, Gitle Mikkelsen, Gemini00, Benjamin Mahoney, Christopher DiBattista, Mandy Reid, Gary Reckard, Sataporn Chaochonpun, Bigolf, Moses Malone, Kyle Merryman, Dante Bencivenga, Zeus Laser, Jake Wise, Jade, Fontaine Liu, Manav parmar, ethnicolor\n\nHelp us caption & translate this video!https://www.youtube.com/timedtext_cs_panel?c=UCsXVk37bltHxD1rDPwtNM8Q&tab=2"
        },
        "defaultAudioLanguage": "en"
      }
    }
  ]
}
